examples/predict_example.py
subject_predictor/__init__.py
subject_predictor/embedding_loader.py
subject_predictor/models.py
subject_predictor/predictor.py
subject_predictor/utils.py
tests/__init__.py
tests/test_models.py
tests/test_predictor.py
subject_predictor-0.1.4.dist-info/METADATA
subject_predictor-0.1.4.dist-info/WHEEL
subject_predictor-0.1.4.dist-info/entry_points.txt
subject_predictor-0.1.4.dist-info/top_level.txt
subject_predictor-0.1.4.dist-info/RECORD
